logging_handler/__init__.py
logging_handler/eventhub_handler.py
eventhub_logging-0.0.3.dist-info/LICENSE.txt
eventhub_logging-0.0.3.dist-info/METADATA
eventhub_logging-0.0.3.dist-info/WHEEL
eventhub_logging-0.0.3.dist-info/top_level.txt
eventhub_logging-0.0.3.dist-info/RECORD
